runno/types.py
runno/.gitignore
runno/__init__.py
runno/LICENSE
runno/runno
runno/main.py
runno-0.2.1.dist-info/METADATA
runno-0.2.1.dist-info/RECORD
runno-0.2.1.dist-info/WHEEL
