Metadata-Version: 2.4
Name: runno
Version: 0.2.1
Summary: Run untrusted code inside the Runno WebAssembly sandbox.
Project-URL: Homepage, https://runno.dev
Author-email: Ben Taylor <me@taybenlor.com>
Maintainer-email: Ben Taylor <me@taybenlor.com>
License-Expression: MIT
Classifier: Development Status :: 3 - Alpha
Classifier: Intended Audience :: Developers
Classifier: License :: OSI Approved :: MIT License
Classifier: Programming Language :: Python :: 3
Classifier: Programming Language :: Python :: 3.13
Classifier: Topic :: System
Requires-Python: >=3.13
Requires-Dist: pydantic~=2.10.4
Provides-Extra: dev
Requires-Dist: black~=24.10.0; extra == 'dev'
